{
  "nl": "Dutch",
  "en": "English",
  "fr": "French",
  "de": "German",
  "it": "Italian",
  "pl": "Polish",
  "pt": "Portuguese",
  "ru": "Russian",
  "es": "Spanish",
  "tr": "Turkish",
  "vi": "Vietnamese",
  "ar": "Arabic",
  "zh": "Chinese",
  "ja": "Japanese",
  "ko": "Korean",
  "th": "Thai",
  "af": "Afrikaans",
  "sq": "Albanian",
  "am": "Amharic",
  "hy": "Armenian",
  "az": "Azerbaijan",
  "ba": "Bashkir",
  "eu": "Basque",
  "be": "Belarusian",
  "bn": "Bengali",
  "bs": "Bosnian",
  "bg": "Bulgarian",
  "ca": "Catalan",
  "ceb": "Cebuano",
  "hr": "Croatian",
  "cs": "Czech",
  "da": "Danish",
  "eo": "Esperanto",
  "et": "Estonian",
  "fi": "Finnish",
  "gl": "Galician",
  "ka": "Georgian",
  "el": "Greek",
  "gu": "Gujarati",
  "ht": "Haitian (Creole)",
  "he": "Hebrew",
  "mrj": "Hill Mari",
  "hi": "Hindi",
  "hu": "Hungarian",
  "is": "Icelandic",
  "id": "Indonesian",
  "ga": "Irish",
  "jv": "Javanese",
  "kn": "Kannada",
  "kk": "Kazakh",
  "ky": "Kyrgyz",
  "la": "Latin",
  "lv": "Latvian",
  "lt": "Lithuanian",
  "mk": "Macedonian",
  "mg": "Malagasy",
  "ms": "Malay",
  "ml": "Malayalam",
  "mt": "Maltese",
  "mi": "Maori",
  "mr": "Marathi",
  "mhr": "Mari",
  "mn": "Mongolian",
  "ne": "Nepali",
  "no": "Norwegian",
  "pap": "Papiamento",
  "fa": "Persian",
  "pa": "Punjabi",
  "ro": "Romanian",
  "gd": "Scottish Gaelic",
  "sr": "Serbian",
  "si": "Sinhala",
  "sk": "Slovakian",
  "sl": "Slovenian",
  "su": "Sundanese",
  "sw": "Swahili",
  "sv": "Swedish",
  "tl": "Tagalog",
  "tg": "Tajik",
  "ta": "Tamil",
  "tt": "Tatar",
  "te": "Telugu",
  "udm": "Udmurt",
  "uk": "Ukrainian",
  "ur": "Urdu",
  "uz": "Uzbek",
  "cy": "Welsh",
  "xh": "Xhosa",
  "yi": "Yiddish"
}
